keytree/__init__.py
keytree/compat.py
keytree/factory.py
keytree/kml.py
keytree/model.py
keytree/tests/__init__.py
keytree/tests/test_read.py
keytree/tests/test_write.py
keytree-1.1.0.dist-info/LICENSE
keytree-1.1.0.dist-info/METADATA
keytree-1.1.0.dist-info/WHEEL
keytree-1.1.0.dist-info/top_level.txt
keytree-1.1.0.dist-info/RECORD
