Metadata-Version: 2.1
Name: keytree
Version: 1.1.0
Summary: KML utilities for the ElementTree API
Home-page: https://github.com/Toblerity/keytree
Author: Sean Gillies
Author-email: sean.gillies@gmail.com
License: BSD
Keywords: KML etree ElementTree
Platform: UNKNOWN
Classifier: Development Status :: 6 - Mature
Classifier: Intended Audience :: Developers
Classifier: Intended Audience :: Science/Research
Classifier: License :: OSI Approved :: BSD License
Classifier: Operating System :: OS Independent
Classifier: Programming Language :: Python
Classifier: Topic :: Scientific/Engineering :: GIS
